podcasthandler-0.6.2.data/scripts/podcasthandler
podcasthandler-0.6.2.data/scripts/podcasthandlerd
podcasthnd/__init__.py
podcasthnd/constants.py
podcasthnd/gui.py
podcasthnd/item.py
podcasthnd/media.py
podcasthandler-0.6.2.dist-info/LICENSE
podcasthandler-0.6.2.dist-info/METADATA
podcasthandler-0.6.2.dist-info/WHEEL
podcasthandler-0.6.2.dist-info/top_level.txt
podcasthandler-0.6.2.dist-info/RECORD
