Metadata-Version: 2.1
Name: podcasthandler
Version: 0.6.2
Summary: Easily play podcasts
Home-page: https://github.com/fnt400/podcasthandler
Author: Claudio Barca
Author-email: claudio@barca.mi.it
License: UNKNOWN
Platform: UNKNOWN
Classifier: Programming Language :: Python :: 3
Classifier: License :: OSI Approved :: GNU General Public License v2 (GPLv2)
Classifier: Operating System :: OS Independent
Requires-Dist: python-mpd2 (~=1.0.0)
